{
    "Alabama": [
        "Pitt",
        "Kansas State",
        "Virginia Tech",
        "Ole Miss",
        "LSU",
        "Miss St.",
        "bye",
        "Texas A&M",
        "Arkansas",
        "Tennessee",
        "Vandy",
        "Mizzou",
        "Auburn"
    ],
    "Texas A&M": [
        "Michigan",
        "TCU",
        "Texas Tech",
        "bye",
        "Miss St.",
        "Arkansas",
        "Ole Miss",
        "Alabama",
        "Auburn",
        "Vandy",
        "Mizzou",
        "Georgia",
        "LSU"
    ],
    "Ole Miss": [
        "Boston College",
        "Iowa",
        "Duke",
        "Alabama",
        "Auburn",
        "bye",
        "Texas A&M",
        "Arkansas",
        "LSU",
        "South Carolina",
        "Kentucky",
        "Florida",
        "Miss St."
    ],
    "Auburn": [
        "Purdue",
        "NC State",
        "Georgia Tech",
        "Arkansas",
        "Ole Miss",
        "LSU",
        "Miss St.",
        "bye",
        "Texas A&M",
        "Kentucky",
        "Florida",
        "Tennessee",
        "Alabama"
    ],
    "Miss St.": [
        "TCU",
        "Rutgers",
        "Purdue",
        "LSU",
        "Texas A&M",
        "Alabama",
        "Arkansas",
        "Auburn",
        "bye",
        "Georgia",
        "South Carolina",
        "Kentucky",
        "Ole Miss"
    ],
    "Arkansas": [
        "Indiana",
        "Wisconsin",
        "Auburn",
        "bye",
        "Texas A&M",
        "Miss St.",
        "Ole Miss",
        "LSU",
        "Alabama",
        "Florida",
        "Tennessee",
        "Vandy",
        "Mizzou"
    ],
    "LSU": [
        "Iowa State",
        "Illinois",
        "UNC",
        "Miss St.",
        "Alabama",
        "Auburn",
        "bye",
        "Arkansas",
        "Ole Miss",
        "Mizzou",
        "Georgia",
        "South Carolina",
        "Texas A&M"
    ],
    "Georgia": [
        "Kansas",
        "Maryland",
        "FCS",
        "South Carolina",
        "Kentucky",
        "Florida",
        "Tennessee",
        "Vandy",
        "Mizzou",
        "bye",
        "Miss St.",
        "LSU",
        "Texas A&M"
    ],
    "Kentucky": [
        "Virginia Tech",
        "Michigan",
        "FCS",
        "bye",
        "Georgia",
        "Tennessee",
        "Mizzou",
        "South Carolina",
        "Florida",
        "Vandy",
        "Auburn",
        "Ole Miss",
        "Miss St."
    ],
    "Tennessee": [
        "Maryland",
        "Clemson",
        "Iowa",
        "bye",
        "Kentucky",
        "Georgia",
        "Mizzou",
        "South Carolina",
        "Florida",
        "Alabama",
        "Arkansas",
        "Auburn",
        "Vandy"
    ],
    "Florida": [
        "Baylor",
        "Iowa State",
        "FCS",
        "Mizzou",
        "South Carolina",
        "Georgia",
        "Vandy",
        "bye",
        "Kentucky",
        "Tennessee",
        "Arkansas",
        "Auburn",
        "Ole Miss"
    ],
    "Mizzou": [
        "Michigan State",
        "Duke",
        "Florida",
        "Vandy",
        "bye",
        "Kentucky",
        "Tennessee",
        "Georgia",
        "South Carolina",
        "LSU",
        "Texas A&M",
        "Alabama",
        "Arkansas"
    ],
    "South Carolina": [
        "Nebraska",
        "Minnesota",
        "FCS",
        "Georgia",
        "Florida",
        "Vandy",
        "bye",
        "Kentucky",
        "Tennessee",
        "Mizzou",
        "Ole Miss",
        "Miss St.",
        "LSU"
    ],
    "Vandy": [
        "Georgia Tech",
        "Texas Tech",
        "Texas",
        "Mizzou",
        "South Carolina",
        "Florida",
        "Georgia",
        "bye",
        "Kentucky",
        "Texas A&M",
        "Alabama",
        "Arkansas",
        "Tennessee"
    ],
    "Wake Forest": [
        "Iowa",
        "Michigan State",
        "OU",
        "bye",
        "Clemson",
        "NC State",
        "Louiville",
        "Boston College",
        "Syracuse",
        "FSU",
        "Pitt",
        "Miami",
        "Virginia Tech"
    ],
    "NC State": [
        "Texas Tech",
        "Auburn",
        "FSU",
        "bye",
        "Wake Forest",
        "Clemson",
        "Louiville",
        "Boston College",
        "Syracuse",
        "Duke",
        "Pitt",
        "Miami",
        "UNC"
    ],
    "Clemson": [
        "Ohio State",
        "Tennessee",
        "FCS",
        "Boston College",
        "Wake Forest",
        "Syracuse",
        "NC State",
        "FSU",
        "Louiville",
        "bye",
        "Georgia Tech",
        "Duke",
        "Pitt"
    ],
    "Louiville": [
        "Rutgers",
        "Ohio State",
        "FCS",
        "Syracuse",
        "FSU",
        "bye",
        "Wake Forest",
        "NC State",
        "Clemson",
        "Boston College",
        "UNC",
        "Georgia Tech",
        "Duke"
    ],
    "FSU": [
        "Minnesota",
        "Indiana",
        "FCS",
        "NC State",
        "Louiville",
        "Boston College",
        "Syracuse",
        "Clemson",
        "bye",
        "Wake Forest",
        "Virginia",
        "UNC",
        "Georgia Tech"
    ],
    "Syracuse": [
        "Texas",
        "Purdue",
        "Kansas State",
        "Louiville",
        "Boston College",
        "Clemson",
        "FSU",
        "bye",
        "Wake Forest",
        "NC State",
        "Virginia Tech",
        "Virginia",
        "UNC"
    ],
    "Boston College": [
        "Ole Miss",
        "Northwestern",
        "Oklahoma State",
        "Clemson",
        "Syracuse",
        "FSU",
        "bye",
        "Wake Forest",
        "NC State",
        "Louiville",
        "Miami",
        "Virginia Tech",
        "Virginia"
    ],
    "Pitt": [
        "Alabama",
        "OU",
        "FCS",
        "Virginia",
        "Georgia Tech",
        "bye",
        "UNC",
        "Virginia Tech",
        "Duke",
        "Miami",
        "Wake Forest",
        "NC State",
        "Clemson"
    ],
    "Miami": [
        "Wisconsin",
        "Kansas",
        "Maryland",
        "Duke",
        "Virginia",
        "Georgia Tech",
        "bye",
        "UNC",
        "Virginia Tech",
        "Pitt",
        "Boston College",
        "Wake Forest",
        "NC State"
    ],
    "Virginia Tech": [
        "Kentucky",
        "Nebraska",
        "Alabama",
        "Georgia Tech",
        "bye",
        "UNC",
        "Duke",
        "Pitt",
        "Miami",
        "Syracuse",
        "Boston College",
        "Wake Forest",
        "Virginia"
    ],
    "Virginia": [
        "Illinois",
        "Penn State",
        "TCU",
        "Pitt",
        "Miami",
        "Duke",
        "Georgia Tech",
        "bye",
        "UNC",
        "FSU",
        "Syracuse",
        "Boston College",
        "Virginia Tech"
    ],
    "UNC": [
        "Oklahoma State",
        "West Virginia",
        "LSU",
        "bye",
        "Duke",
        "Virginia Tech",
        "Pitt",
        "Miami",
        "Virginia",
        "Georgia Tech",
        "Louiville",
        "FSU",
        "Syracuse"
    ],
    "Georgia Tech": [
        "Vandy",
        "Texas",
        "Auburn",
        "Virginia Tech",
        "Pitt",
        "Miami",
        "Virginia",
        "Duke",
        "bye",
        "UNC",
        "Clemson",
        "Louiville",
        "FSU"
    ],
    "Duke": [
        "Northwestern",
        "Mizzou",
        "Ole Miss",
        "Miami",
        "UNC",
        "Virginia",
        "Virginia Tech",
        "Georgia Tech",
        "Pitt",
        "bye",
        "NC State",
        "Clemson",
        "Louiville"
    ],
    "Oklahoma State": [
        "UNC",
        "FCS",
        "Boston College",
        "Baylor",
        "Kansas State",
        "Iowa State",
        "Texas",
        "West Virginia",
        "TCU",
        "Texas Tech",
        "Kansas",
        "OU",
        "bye"
    ],
    "Baylor": [
        "Florida",
        "FCS",
        "Indiana",
        "Oklahoma State",
        "TCU",
        "Texas Tech",
        "Kansas",
        "West Virginia",
        "OU",
        "Kansas State",
        "Iowa State",
        "Texas",
        "bye"
    ],
    "OU": [
        "Penn State",
        "Pitt",
        "Wake Forest",
        "Texas",
        "TCU",
        "Texas Tech",
        "Kansas",
        "Baylor",
        "West Virginia",
        "Kansas State",
        "Iowa State",
        "Oklahoma State",
        "bye"
    ],
    "Iowa State": [
        "LSU",
        "Florida",
        "Wisconsin",
        "Kansas State",
        "West Virginia",
        "Texas",
        "Oklahoma State",
        "TCU",
        "Texas Tech",
        "Kansas",
        "Baylor",
        "OU",
        "bye"
    ],
    "Kansas State": [
        "FCS",
        "Alabama",
        "Syracuse",
        "Iowa State",
        "Texas",
        "Oklahoma State",
        "TCU",
        "Texas Tech",
        "Baylor",
        "OU",
        "West Virginia",
        "Kansas",
        "bye"
    ],
    "West Virginia": [
        "FCS",
        "UNC",
        "FCS",
        "Texas Tech",
        "Iowa State",
        "Kansas",
        "Texas",
        "Baylor",
        "Oklahoma State",
        "OU",
        "TCU",
        "Kansas State",
        "bye"
    ],
    "Texas": [
        "Syracuse",
        "Georgia Tech",
        "Vandy",
        "OU",
        "Kansas State",
        "Iowa State",
        "West Virginia",
        "Oklahoma State",
        "TCU",
        "Texas Tech",
        "Kansas",
        "Baylor",
        "bye"
    ],
    "TCU": [
        "Miss St.",
        "Texas A&M",
        "Virginia",
        "Kansas",
        "Baylor",
        "OU",
        "Kansas State",
        "Iowa State",
        "Texas",
        "Oklahoma State",
        "West Virginia",
        "Texas Tech",
        "bye"
    ],
    "Texas Tech": [
        "NC State",
        "Vandy",
        "Texas A&M",
        "West Virginia",
        "Kansas",
        "Baylor",
        "OU",
        "Kansas State",
        "Iowa State",
        "Texas",
        "Oklahoma State",
        "TCU",
        "bye"
    ],
    "Kansas": [
        "Georgia",
        "Miami",
        "Illinois",
        "TCU",
        "Texas Tech",
        "West Virginia",
        "Baylor",
        "OU",
        "Iowa State",
        "Texas",
        "Oklahoma State",
        "Kansas State",
        "bye"
    ],
    "Iowa": [
        "Wake Forest",
        "Ole Miss",
        "Tennessee",
        "Illinois",
        "Purdue",
        "Minnesota",
        "Wisconsin",
        "Northwestern",
        "bye",
        "Nebraska",
        "Michigan",
        "Ohio State",
        "Michigan State"
    ],
    "Minnesota": [
        "FSU",
        "South Carolina",
        "FCS",
        "Northwestern",
        "Iowa",
        "bye",
        "Nebraska",
        "Illinois",
        "Purdue",
        "Indiana",
        "Michigan",
        "Ohio State",
        "Wisconsin"
    ],
    "Wisconsin": [
        "Miami",
        "Arkansas",
        "Iowa State",
        "Purdue",
        "Northwestern",
        "Iowa",
        "bye",
        "Nebraska",
        "Illinois",
        "Rutgers",
        "Indiana",
        "Michigan",
        "Minnesota"
    ],
    "Purdue": [
        "Auburn",
        "Syracuse",
        "Miss St.",
        "Wisconsin",
        "Iowa",
        "bye",
        "Nebraska",
        "Illinois",
        "Northwestern",
        "Minnesota",
        "Maryland",
        "Rutgers",
        "Indiana"
    ],
    "Illinois": [
        "Virginia",
        "LSU",
        "Kansas",
        "Iowa",
        "bye",
        "Nebraska",
        "Purdue",
        "Minnesota",
        "Wisconsin",
        "Penn State",
        "Maryland",
        "Rutgers",
        "Northwestern"
    ],
    "Nebraska": [
        "South Carolina",
        "Virginia Tech",
        "FCS",
        "bye",
        "Northwestern",
        "Illinois",
        "Purdue",
        "Minnesota",
        "Wisconsin",
        "Iowa",
        "Michigan State",
        "Penn State",
        "Maryland"
    ],
    "Northwestern": [
        "Duke",
        "Boston College",
        "Minnesota",
        "Nebraska",
        "Wisconsin",
        "Iowa",
        "Purdue",
        "bye",
        "Ohio State",
        "Michigan State",
        "Penn State",
        "Illinois",
        "Illinois"
    ],
    "Michigan": [
        "Texas A&M",
        "Kentucky",
        "FCS",
        "bye",
        "Penn State",
        "Michigan State",
        "Maryland",
        "Indiana",
        "Rutgers",
        "Iowa",
        "Minnesota",
        "Wisconsin",
        "Ohio State"
    ],
    "Ohio State": [
        "Clemson",
        "Louiville",
        "FCS",
        "Maryland",
        "Indiana",
        "Penn State",
        "Rutgers",
        "Michigan State",
        "bye",
        "Northwestern",
        "Iowa",
        "Minnesota",
        "Michigan"
    ],
    "Michigan State": [
        "Mizzou",
        "Wake Forest",
        "FCS",
        "Indiana",
        "Rutgers",
        "bye",
        "Michigan",
        "Ohio State",
        "Maryland",
        "Nebraska",
        "Northwestern",
        "Iowa",
        "Penn State"
    ],
    "Penn State": [
        "OU",
        "Virginia",
        "FCS",
        "Rutgers",
        "bye",
        "Michigan",
        "Ohio State",
        "Maryland",
        "Indiana",
        "Illinois",
        "Nebraska",
        "Northwestern",
        "Michigan State"
    ],
    "Maryland": [
        "Tennessee",
        "Georgia",
        "Miami",
        "Ohio State",
        "Indiana",
        "bye",
        "Michigan",
        "Penn State",
        "Michigan State",
        "Purdue",
        "Illinois",
        "Nebraska",
        "Rutgers"
    ],
    "Rutgers": [
        "Louiville",
        "Miss St.",
        "FCS",
        "Penn State",
        "Michigan State",
        "Indiana",
        "Ohio State",
        "bye",
        "Michigan",
        "Wisconsin",
        "Purdue",
        "Illinois",
        "Maryland"
    ],
    "Indiana": [
        "Arkansas",
        "FSU",
        "Baylor",
        "Michigan State",
        "Maryland",
        "Ohio State",
        "Rutgers",
        "bye",
        "Michigan",
        "Penn State",
        "Minnesota",
        "Wisconsin",
        "Purdue"
    ]
}